dash_glide_grid/GlideGrid.py
dash_glide_grid/__init__.py
dash_glide_grid/_imports_.py
dash_glide_grid/async-null.js
dash_glide_grid/async-null.js.map
dash_glide_grid/dash_glide_grid.min.js
dash_glide_grid/dash_glide_grid.min.js.map
dash_glide_grid/metadata.json
dash_glide_grid/package-info.json
dash_glide_grid-0.1.8.dist-info/licenses/LICENSE
dash_glide_grid-0.1.8.dist-info/METADATA
dash_glide_grid-0.1.8.dist-info/WHEEL
dash_glide_grid-0.1.8.dist-info/top_level.txt
dash_glide_grid-0.1.8.dist-info/RECORD
