Metadata-Version: 2.4
Name: dash-glide-grid
Version: 0.1.8
Summary: A high-performance data grid component for Plotly Dash
Author: Ben Weinberg
License: MIT
Project-URL: Homepage, https://github.com/benweinberg89/dash-glide-grid
Project-URL: Repository, https://github.com/benweinberg89/dash-glide-grid
Classifier: Framework :: Dash
Classifier: Programming Language :: Python :: 3
Classifier: Programming Language :: Python :: 3.9
Classifier: Programming Language :: Python :: 3.10
Classifier: Programming Language :: Python :: 3.11
Classifier: Programming Language :: Python :: 3.12
Classifier: Programming Language :: Python :: 3.13
Classifier: License :: OSI Approved :: MIT License
Classifier: Operating System :: OS Independent
Requires-Python: >=3.9
License-File: LICENSE
Requires-Dist: dash>=3.3
Dynamic: license-file
